yta_audio_advanced/__init__.py
yta_audio_advanced/audio.py
yta_audio_advanced-0.0.2.dist-info/LICENSE
yta_audio_advanced-0.0.2.dist-info/METADATA
yta_audio_advanced-0.0.2.dist-info/WHEEL
yta_audio_advanced-0.0.2.dist-info/RECORD
