Metadata-Version: 2.3
Name: yta-audio-advanced
Version: 0.0.2
Summary: Youtube Autonomous Advanced Audio Module.
Author: danialcala94
Author-email: danielalcalavalera@gmail.com
Requires-Python: ==3.9
Classifier: Programming Language :: Python :: 3
Classifier: Programming Language :: Python :: 3.9
Requires-Dist: numpy (>=0.0.1,<9.0.0)
Requires-Dist: yta_audio_advanced_filters (>=0.0.1,<1.0.0)
Requires-Dist: yta_audio_base (>=0.0.1,<1.0.0)
Requires-Dist: yta_validation (>=0.0.1,<1.0.0)
